<Properties StartupConfiguration="{5598BB2D-3CF0-45E5-878C-5894B3B04B70}|https">
  <MonoDevelop.Ide.DebuggingService.Breakpoints>
    <BreakpointStore />
  </MonoDevelop.Ide.DebuggingService.Breakpoints>
  <MonoDevelop.Ide.DebuggingService.PinnedWatches />
  <MultiItemStartupConfigurations />
  <MonoDevelop.Ide.Workspace ActiveConfiguration="Debug" />
  <MonoDevelop.Ide.Workbench ActiveDocument="LibraryWebServer/Controllers/HomeController.cs">
    <Files>
      <File FileName="LibraryWebServer/Controllers/HomeController.cs" Line="98" Column="25" />
      <File FileName="LibraryWebServer/Models/Patrons.cs" />
      <File FileName="LibraryWebServer/Models/CheckedOut.cs" />
    </Files>
    <Pads>
      <Pad Id="ProjectPad">
        <State name="__root__">
          <Node name="LibraryWebServer">
            <Node name="LibraryWebServer">
              <Node name="Controllers" expanded="True">
                <Node name="HomeController.cs" selected="True" />
              </Node>
              <Node name="Models" expanded="True" />
            </Node>
          </Node>
        </State>
      </Pad>
      <Pad Id="MonoDevelop.Debugger.WatchPad">
        <State />
      </Pad>
    </Pads>
  </MonoDevelop.Ide.Workbench>
  <Xamarin.Addins.Core.Project ActiveDebugTarget="MyAppleMacCatalystID" />
  <MonoDevelop.Ide.ItemProperties.LibraryWebServer PreferredExecutionTarget="/Applications/Google Chrome.app" />
</Properties>